SHop_src/SHop.py
SHop_src/SHop_E260_90m_1h_execution.py
SHop_src/__init__.py
SHop-0.0.1.dist-info/LICENSE
SHop-0.0.1.dist-info/METADATA
SHop-0.0.1.dist-info/WHEEL
SHop-0.0.1.dist-info/top_level.txt
SHop-0.0.1.dist-info/RECORD
